dungeonmaker/__init__.py
dungeonmaker/dm_backend/__init__.py
dungeonmaker/dm_backend/backend.py
dungeonmaker/dm_backend/modules/__init__.py
dungeonmaker/dm_backend/modules/database/__init__.py
dungeonmaker/dm_backend/modules/database/basetypes.py
dungeonmaker/dm_backend/modules/database/connection.py
dungeonmaker/dm_backend/modules/database/dba.py
dungeonmaker/dm_backend/modules/dm/__init__.py
dungeonmaker/dm_backend/modules/dm/dba.py
dungeonmaker/dm_backend/modules/dm/dmtypes.py
dungeonmaker/dm_backend/modules/dm/dungeon.py
dungeonmaker/dm_backend/modules/dm/room.py
dungeonmaker/dm_backend/modules/dm/selectors.py
dungeonmaker/dm_backend/modules/dm/session.py
dungeonmaker/dm_backend/modules/dm/user.py
dungeonmaker/dm_backend/modules/dm/utils.py
dungeonmaker-0.6.13.dist-info/LICENSE
dungeonmaker-0.6.13.dist-info/METADATA
dungeonmaker-0.6.13.dist-info/WHEEL
dungeonmaker-0.6.13.dist-info/top_level.txt
dungeonmaker-0.6.13.dist-info/RECORD
