Metadata-Version: 2.1
Name: dungeonmaker
Version: 0.6.13
Summary: Dungeon maker backend and other things
Home-page: https://github.com/thecommcraft/dungeon-maker-reinvented
Author: Simon Gilde
Author-email: simon.c.gilde@gmail.com
Keywords: scratch
Classifier: Development Status :: 4 - Beta
Classifier: Intended Audience :: Developers
Classifier: License :: OSI Approved :: MIT License
Classifier: Programming Language :: Python :: 3.11
Requires-Python: >=3.11
License-File: LICENSE
Requires-Dist: scratchcommunication
Requires-Dist: pymongo
Requires-Dist: scratchattach
